crud_management/__init__.py
crud_management/admin.py
crud_management/apps.py
crud_management/models.py
crud_management/tests.py
crud_management/views.py
crud_management/management/__init__.py
crud_management/management/commands/__init__.py
crud_management/management/commands/generate_crud.py
crud_management/management/commands/generate_crud_views.py
crud_management/migrations/__init__.py
drf_crud_command-0.3.dist-info/LICENSE
drf_crud_command-0.3.dist-info/METADATA
drf_crud_command-0.3.dist-info/WHEEL
drf_crud_command-0.3.dist-info/top_level.txt
drf_crud_command-0.3.dist-info/RECORD
