Metadata-Version: 2.1
Name: drf-crud-command
Version: 0.3
Summary: django rest management command for dynamic write crud api
Home-page: https://www.trootech.com/
Author: Dharmrajsinh Gohil
Author-email: dharmrajsinh.gohil@trootech.com
Maintainer: Dharmrajsinh
Maintainer-email: dharmrajsinh.gohil@trootech.com
License: MIT
Keywords: drf crud command
Classifier: Development Status :: 4 - Beta
Classifier: Environment :: Web Environment
Classifier: Intended Audience :: Developers
Classifier: License :: OSI Approved :: MIT License
Classifier: Operating System :: OS Independent
Classifier: Programming Language :: Python :: 3 :: Only
Classifier: Programming Language :: Python :: 3.8
Classifier: Programming Language :: Python :: Implementation :: CPython
Classifier: Topic :: Software Development :: Libraries :: Application Frameworks
Classifier: Topic :: Software Development :: Libraries :: Python Modules
License-File: LICENSE
